CHANGES
LICENSE
MANIFEST.in
README.rst
setup.py
landez/__init__.py
landez/cache.py
landez/filters.py
landez/proj.py
landez/sources.py
landez/tests.py
landez/tiles.py
landez/util.py
landez.egg-info/PKG-INFO
landez.egg-info/SOURCES.txt
landez.egg-info/dependency_links.txt
landez.egg-info/not-zip-safe
landez.egg-info/requires.txt
landez.egg-info/top_level.txt