Metadata-Version: 1.1
Name: landez
Version: 2.3.0
Summary: Landez is a python toolbox to manipulate map tiles.
Home-page: https://github.com/makinacorpus/landez/
Author: Mathieu Leplatre
Author-email: mathieu.leplatre@makina-corpus.com
License: LPGL, see LICENSE file.
Download-URL: http://pypi.python.org/pypi/landez/
Keywords: MBTiles,Mapnik
Platform: UNKNOWN
Classifier: Programming Language :: Python :: 2.6
Classifier: Natural Language :: English
Classifier: Topic :: Utilities
Classifier: Development Status :: 5 - Production/Stable
